LICENSE
hallucinations/__init__.py
hallucinations-0.1.4.dist-info/LICENSE
hallucinations-0.1.4.dist-info/WHEEL
hallucinations-0.1.4.dist-info/METADATA
hallucinations-0.1.4.dist-info/RECORD
