Metadata-Version: 2.1
Name: hallucinations
Version: 0.1.4
Summary: 
Home-page: https://github.com/RodolfoFerro/hallucinations
License: MIT
Author: Rodolfo Ferro
Author-email: rodolfoferroperez@gmail.com
Requires-Python: >=3.6,<4.0
Classifier: License :: OSI Approved :: MIT License
Classifier: Operating System :: OS Independent
Classifier: Programming Language :: Python :: 3
Classifier: Programming Language :: Python :: 3.6
Classifier: Programming Language :: Python :: 3.7
Requires-Dist: matplotlib (>=3.1,<4.0)
Requires-Dist: numba (>=0.45.1,<0.46.0)
Project-URL: Repository, https://github.com/RodolfoFerro/hallucinations
